plasmidin/__init__.py
plasmidin/plasmid_diagrams.py
plasmidin/plasmidin.py
plasmidin/plasmidin_exceptions.py
plasmidin-1.0.0.dist-info/METADATA
plasmidin-1.0.0.dist-info/WHEEL
plasmidin-1.0.0.dist-info/top_level.txt
plasmidin-1.0.0.dist-info/RECORD
