Metadata-Version: 2.1
Name: plasmidin
Version: 1.0.0
Summary: A package to look at inserting DNA sequences into plasmids for cloning or PCR for SWBio DTP Data Science and Machine Learning Module
Home-page: https://github.com/bmm514/PlasmidInsertChecker.git
Author: Ben Murcott
Author-email: Ben Murcott <bmm41@bath.ac.uk>
Project-URL: Homepage, https://https://github.com/bmm514/PlamidInsertChecker
Project-URL: Issues, https://https://github.com/bmm514/PlamidInsertChecker/issues
Classifier: Programming Language :: Python :: 3
Classifier: Operating System :: OS Independent
Requires-Python: >=3.8
Requires-Dist: biopython ==1.81
Requires-Dist: numpy ==1.26.2
Requires-Dist: pandas ==2.1.3
Requires-Dist: reportlab ==4.0.8
